CHANGELOG.txt
MANIFEST.in
README.txt
pymd.py
setup.py
pymd.egg-info/PKG-INFO
pymd.egg-info/SOURCES.txt
pymd.egg-info/dependency_links.txt
pymd.egg-info/not-zip-safe
pymd.egg-info/requires.txt
pymd.egg-info/top_level.txt
tests/test_pymd.py