Metadata-Version: 1.1
Name: pymd
Version: 0.5.5
Summary: wrapper for python markdown but having a full HTML for the output (and nice things)
Home-page: https://github.com/eikiu/pymd
Author: Ei Kiu
Author-email: eikiu.inc@gmail.com
License: MIT
Keywords: markdown,html
Platform: UNKNOWN
Classifier: Development Status :: 4 - Beta
Classifier: Environment :: Console
Classifier: Intended Audience :: End Users/Desktop
Classifier: License :: OSI Approved :: MIT License
Classifier: Operating System :: OS Independent
Classifier: Programming Language :: Python
Classifier: Programming Language :: Python :: 2
Classifier: Programming Language :: Python :: 2.7
Classifier: Programming Language :: Python :: 3
Classifier: Programming Language :: Python :: 3.3
Classifier: Topic :: Documentation
Classifier: Topic :: Software Development :: Documentation
Classifier: Topic :: Text Processing
Classifier: Topic :: Text Processing :: Markup :: HTML
Classifier: Topic :: Utilities
